{
  "credit": "Made with Blockbench",
  "parent": "block/thin_block",
  "texture_size": [32, 32],
  "render_type": "translucent",
  "textures": {
    "1": "redstoneplus:block/oxidized_copper",
    "2": "redstoneplus:block/smooth_stone",
    "4": "redstoneplus:block/receiver",
    "particle": "redstoneplus:block/smooth_stone"
  },
  "elements": [
    {
      "name": "Base",
      "from": [2, 2, 0],
      "to": [14, 14, 2],
      "faces": {
        "north": {"uv": [14.85714, 1.14286, 1.14286, 14.85714], "texture": "#2"},
        "east": {"uv": [13.71429, 1.14286, 16, 14.85714], "texture": "#2"},
        "south": {"uv": [1.14286, 1.14286, 14.85714, 14.85714], "rotation": 90, "texture": "#2"},
        "west": {"uv": [1.14286, 13.71429, 14.85714, 16], "rotation": 90, "texture": "#2"},
        "up": {"uv": [1.14286, 0, 14.85714, 2.28571], "texture": "#2"},
        "down": {"uv": [0, 14.85714, 2.28571, 1.14286], "rotation": 90, "texture": "#2"}
      }
    },
    {
      "name": "Antenna",
      "from": [1, 10, 0],
      "to": [2, 21, 1],
      "faces": {
        "north": {"uv": [3, 0, 4, 11], "texture": "#1"},
        "east": {"uv": [3, 0, 4, 11], "texture": "#1"},
        "south": {"uv": [3, 0, 4, 11], "texture": "#1"},
        "west": {"uv": [3, 0, 4, 11], "texture": "#1"},
        "up": {"uv": [3, 0, 4, 1], "texture": "#1"},
        "down": {"uv": [3, 10, 4, 11], "texture": "#1"}
      }
    },
    {
      "name": "Receiver",
      "from": [-1, 19, -2],
      "to": [4, 19, 3],
      "faces": {
        "north": {"uv": [0, 0, 2.5, 0], "texture": "#missing"},
        "east": {"uv": [0, 0, 2.5, 0], "texture": "#missing"},
        "south": {"uv": [0, 0, 2.5, 0], "texture": "#missing"},
        "west": {"uv": [0, 0, 2.5, 0], "texture": "#missing"},
        "up": {"uv": [0, 0, 16, 16], "texture": "#4"},
        "down": {"uv": [0, 0, 16, 16], "texture": "#4"}
      }
    }
  ],
  "display": {
    "thirdperson_righthand": {
      "rotation": [70, 0, -7],
      "translation": [0, 4.75, 3],
      "scale": [0.75, 0.75, 0.75]
    },
    "thirdperson_lefthand": {
      "rotation": [70, 0, 7],
      "translation": [0, 4.75, 3],
      "scale": [0.75, 0.75, 0.75]
    },
    "firstperson_righthand": {
      "translation": [0, 7.25, 0]
    },
    "firstperson_lefthand": {
      "translation": [0, 7.25, 0]
    },
    "ground": {
      "translation": [0, 4, 0],
      "scale": [0.5, 0.5, 0.5]
    }
  }
}